<?xml version="1.0" encoding="utf-8"?>
<manifest identifier="_6jDF7n97TT0" version="1.0" xmlns="http://www.imsproject.org/xsd/imscp_rootv1p1p2" xmlns:adlcp="http://www.adlnet.org/xsd/adlcp_rootv1p2" xmlns:xsi="http://www.w3.org/2001/XMLSchema-instance" xsi:schemaLocation="http://www.imsproject.org/xsd/imscp_rootv1p1p2 imscp_rootv1p1p2.xsd http://www.imsglobal.org/xsd/imsmd_rootv1p2p1 imsmd_rootv1p2p1.xsd http://www.adlnet.org/xsd/adlcp_rootv1p2 adlcp_rootv1p2.xsd">
  <metadata>
    <schema>ADL SCORM</schema>
    <schemaversion>1.2</schemaversion>
    <lom xmlns="http://www.imsglobal.org/xsd/imsmd_rootv1p2p1" xmlns:xsi="http://www.w3.org/2001/XMLSchema-instance" xsi:schemaLocation="http://www.imsglobal.org/xsd/imsmd_rootv1p2p1 imsmd_rootv1p2p1.xsd">
      <general>
        <title>
          <langstring xml:lang="x-none">Introduction to VLookup</langstring>
        </title>
      </general>
      <lifecycle>
        <version>
          <langstring xml:lang="x-none">1</langstring>
        </version>
        <status>
          <source>
            <langstring xml:lang="x-none">LOMv1.0</langstring>
          </source>
          <value>
            <langstring xml:lang="x-none">Final</langstring>
          </value>
        </status>
      </lifecycle>
      <metametadata>
        <metadatascheme>ADL SCORM 1.2</metadatascheme>
      </metametadata>
      <educational>
        <typicallearningtime>
          <datetime>PT0H0M0S</datetime>
        </typicallearningtime>
      </educational>
      <rights>
        <cost>
          <source>
            <langstring xml:lang="x-none">LOMv1.0</langstring>
          </source>
          <value>
            <langstring xml:lang="x-none">yes</langstring>
          </value>
        </cost>
        <copyrightandotherrestrictions>
          <source>
            <langstring xml:lang="x-none">LOMv1.0</langstring>
          </source>
          <value>
            <langstring xml:lang="x-none">yes</langstring>
          </value>
        </copyrightandotherrestrictions>
      </rights>
    </lom>
  </metadata>
  <organizations default="Introduction_to_VLookup_ORG">
    <organization identifier="Introduction_to_VLookup_ORG">
      <title>Introduction to VLookup</title>
      <item identifier="Introduction_to_VLookup_SCO" isvisible="true" identifierref="__6jDF7n97TT0_RES">
        <title>Introduction to VLookup</title>
      </item>
    </organization>
  </organizations>
  <resources>
    <resource identifier="__6jDF7n97TT0_RES" type="webcontent" href="index_lms.html" adlcp:scormtype="sco">
      <file href="story_content/thumbnail.jpg" />
      <file href="story_content/6gWEjIfBFEa_44100_48_0.mp3" />
      <file href="mobile/6egM0F5PVqw.png" />
      <file href="story_content/6lRWoPZvx5D_44100_48_0.mp3" />
      <file href="story_content/64mlU4yqVbw_44100_48_0.mp3" />
      <file href="story_content/6haYIvAQShQ_44100_48_0.mp3" />
      <file href="story_content/5rgTx7YCd1B_44100_48_0.mp3" />
      <file href="story_content/6W2Qnohtjqz_44100_48_0.mp3" />
      <file href="story_content/6OfRca6QYre_44100_48_0.mp3" />
      <file href="mobile/5jFGun90L8T.png" />
      <file href="story_content/6G6aXDpouGg_44100_48_0.mp3" />
      <file href="mobile/6UXU0PBOjPe.png" />
      <file href="story_content/6IAzyAb4Eys_44100_48_0.mp3" />
      <file href="mobile/6d7MfvOImNn.png" />
      <file href="story_content/6eDpp3yRYaX_44100_48_0.mp3" />
      <file href="mobile/5ZyZBRE4ojM.png" />
      <file href="mobile/6C9dz0mOAoH.jpg" />
      <file href="mobile/5f54yVpLezX.png" />
      <file href="mobile/5sbnHVvEdpO.png" />
      <file href="mobile/6o7EMfpG6SK.png" />
      <file href="mobile/6TpWI9dXbfM.png" />
      <file href="mobile/6WErVdTJcga.png" />
      <file href="mobile/6WYdxMGv5MY.png" />
      <file href="mobile/6h2i2pSVfNZ.png" />
      <file href="mobile/5vLSr7OnJSE.png" />
      <file href="mobile/6AjMFKRagzw.png" />
      <file href="story_content/5d7hFOLmVPC_44100_48_0.mp3" />
      <file href="meta.xml" />
      <file href="story_content/user.js" />
      <file href="html5/data/css/output.min.css" />
      <file href="html5/data/js/5fKl91dqWte.js" />
      <file href="html5/data/js/5luFWGwDZvd.js" />
      <file href="html5/data/js/5oYQP4MTUpV.js" />
      <file href="html5/data/js/5yIrYmYzMn5.js" />
      <file href="html5/data/js/610xcHJDYVJ.js" />
      <file href="html5/data/js/6cOE3DAn7SD.js" />
      <file href="html5/data/js/6EoHcqTxRqf.js" />
      <file href="html5/data/js/6GDWzdR8RVq.js" />
      <file href="html5/data/js/6gdzq42fgjx.js" />
      <file href="html5/data/js/6LxS8LzM5kU.js" />
      <file href="html5/data/js/6PW8xsuWOuc.js" />
      <file href="html5/data/js/data.js" />
      <file href="html5/data/js/frame.js" />
      <file href="html5/data/js/paths.js" />
      <file href="html5/lib/hls/hls.min.js" />
      <file href="html5/lib/scripts/bootstrapper.min.js" />
      <file href="html5/lib/scripts/frame.desktop.min.js" />
      <file href="html5/lib/scripts/frame.mobile.min.js" />
      <file href="html5/lib/scripts/slides.min.js" />
      <file href="html5/lib/stylesheets/desktop.min.css" />
      <file href="html5/lib/stylesheets/mobile.min.css" />
      <file href="html5/lib/stylesheets/mobile-fonts/open-sans-bold.woff" />
      <file href="html5/lib/stylesheets/mobile-fonts/open-sans-light.woff" />
      <file href="html5/lib/stylesheets/mobile-fonts/open-sans-regular.woff" />
      <file href="analytics-frame.html" />
      <file href="story.html" />
      <file href="index_lms.html" />
      <file href="lms/AICCComm.html" />
      <file href="lms/blank.html" />
      <file href="lms/browsersniff.js" />
      <file href="lms/goodbye.html" />
      <file href="lms/scormdriver.js" />
    </resource>
  </resources>
</manifest>