<?xml version="1.0" encoding="utf-8"?>
<manifest identifier="_6MhxxndqlFF" version="1.0" xmlns="http://www.imsproject.org/xsd/imscp_rootv1p1p2" xmlns:adlcp="http://www.adlnet.org/xsd/adlcp_rootv1p2" xmlns:xsi="http://www.w3.org/2001/XMLSchema-instance" xsi:schemaLocation="http://www.imsproject.org/xsd/imscp_rootv1p1p2 imscp_rootv1p1p2.xsd http://www.imsglobal.org/xsd/imsmd_rootv1p2p1 imsmd_rootv1p2p1.xsd http://www.adlnet.org/xsd/adlcp_rootv1p2 adlcp_rootv1p2.xsd">
  <metadata>
    <schema>ADL SCORM</schema>
    <schemaversion>1.2</schemaversion>
    <lom xmlns="http://www.imsglobal.org/xsd/imsmd_rootv1p2p1" xmlns:xsi="http://www.w3.org/2001/XMLSchema-instance" xsi:schemaLocation="http://www.imsglobal.org/xsd/imsmd_rootv1p2p1 imsmd_rootv1p2p1.xsd">
      <general>
        <title>
          <langstring xml:lang="x-none">How to delete Table column - 2 Methods</langstring>
        </title>
      </general>
      <lifecycle>
        <version>
          <langstring xml:lang="x-none">1</langstring>
        </version>
        <status>
          <source>
            <langstring xml:lang="x-none">LOMv1.0</langstring>
          </source>
          <value>
            <langstring xml:lang="x-none">Final</langstring>
          </value>
        </status>
      </lifecycle>
      <metametadata>
        <metadatascheme>ADL SCORM 1.2</metadatascheme>
      </metametadata>
      <educational>
        <typicallearningtime>
          <datetime>PT0H0M0S</datetime>
        </typicallearningtime>
      </educational>
      <rights>
        <cost>
          <source>
            <langstring xml:lang="x-none">LOMv1.0</langstring>
          </source>
          <value>
            <langstring xml:lang="x-none">yes</langstring>
          </value>
        </cost>
        <copyrightandotherrestrictions>
          <source>
            <langstring xml:lang="x-none">LOMv1.0</langstring>
          </source>
          <value>
            <langstring xml:lang="x-none">yes</langstring>
          </value>
        </copyrightandotherrestrictions>
      </rights>
    </lom>
  </metadata>
  <organizations default="How_to_delete_Table_column_-_2_Methods_ORG">
    <organization identifier="How_to_delete_Table_column_-_2_Methods_ORG">
      <title>How to delete Table column - 2 Methods</title>
      <item identifier="How_to_delete_Table_column_-_2_Methods_SCO" isvisible="true" identifierref="__6MhxxndqlFF_RES">
        <title>How to delete Table column - 2 Methods</title>
      </item>
    </organization>
  </organizations>
  <resources>
    <resource identifier="__6MhxxndqlFF_RES" type="webcontent" href="index_lms.html" adlcp:scormtype="sco">
      <file href="story_content/thumbnail.jpg" />
      <file href="story_content/6fzYNCbG07P_44100_48_0.mp3" />
      <file href="mobile/6fSEWxYV5HO.png" />
      <file href="story_content/6Dzv5nJvf1x_44100_48_0.mp3" />
      <file href="mobile/5vJWKWYoyMk.png" />
      <file href="mobile/6XqOg6ieavI_P_0_34_1366_604.png" />
      <file href="story_content/6niJTmNRiqZ_44100_48_0.mp3" />
      <file href="mobile/6GdFbtGPvjL.png" />
      <file href="mobile/6Qcs4v8WCC2_P_0_34_1366_604.png" />
      <file href="story_content/6g6aA3VhW10_44100_48_0.mp3" />
      <file href="mobile/5rqFehKrwQq.png" />
      <file href="story_content/5el9cB0rMSC_44100_48_0.mp3" />
      <file href="mobile/5s2h55woglr.png" />
      <file href="story_content/6Sn3rYkyDXr_44100_48_0.mp3" />
      <file href="mobile/5ZSreryltay.png" />
      <file href="mobile/5gTlo5lBxW6_P_0_34_1366_604.png" />
      <file href="story_content/5pcVOfek9hr_44100_48_0.mp3" />
      <file href="mobile/63c7azHySl3.png" />
      <file href="mobile/6C9dz0mOAoH.jpg" />
      <file href="mobile/5f54yVpLezX.png" />
      <file href="mobile/5sbnHVvEdpO.png" />
      <file href="mobile/6o7EMfpG6SK.png" />
      <file href="mobile/6TpWI9dXbfM.png" />
      <file href="mobile/6WErVdTJcga.png" />
      <file href="mobile/6WYdxMGv5MY.png" />
      <file href="mobile/6h2i2pSVfNZ.png" />
      <file href="mobile/5vLSr7OnJSE.png" />
      <file href="mobile/6AjMFKRagzw.png" />
      <file href="story_content/5d7hFOLmVPC_44100_48_0.mp3" />
      <file href="meta.xml" />
      <file href="story_content/user.js" />
      <file href="html5/data/css/output.min.css" />
      <file href="html5/data/js/5hVgHc51oL2.js" />
      <file href="html5/data/js/5o9uIgHuFCT.js" />
      <file href="html5/data/js/5rFzc4KEtHS.js" />
      <file href="html5/data/js/5tOYANjKJoY.js" />
      <file href="html5/data/js/5UoxH4Q2mLL.js" />
      <file href="html5/data/js/6GRTlJI1QFw.js" />
      <file href="html5/data/js/6K7ddKXQzJ4.js" />
      <file href="html5/data/js/6oe8S1gwhPr.js" />
      <file href="html5/data/js/data.js" />
      <file href="html5/data/js/frame.js" />
      <file href="html5/data/js/paths.js" />
      <file href="html5/lib/hls/hls.min.js" />
      <file href="html5/lib/scripts/bootstrapper.min.js" />
      <file href="html5/lib/scripts/frame.desktop.min.js" />
      <file href="html5/lib/scripts/frame.mobile.min.js" />
      <file href="html5/lib/scripts/slides.min.js" />
      <file href="html5/lib/stylesheets/desktop.min.css" />
      <file href="html5/lib/stylesheets/mobile.min.css" />
      <file href="html5/lib/stylesheets/mobile-fonts/open-sans-bold.woff" />
      <file href="html5/lib/stylesheets/mobile-fonts/open-sans-light.woff" />
      <file href="html5/lib/stylesheets/mobile-fonts/open-sans-regular.woff" />
      <file href="analytics-frame.html" />
      <file href="story.html" />
      <file href="index_lms.html" />
      <file href="lms/AICCComm.html" />
      <file href="lms/blank.html" />
      <file href="lms/browsersniff.js" />
      <file href="lms/goodbye.html" />
      <file href="lms/scormdriver.js" />
    </resource>
  </resources>
</manifest>